cellrank_mcp/__init__.py
cellrank_mcp/cli.py
cellrank_mcp/util.py
cellrank_mcp/schema/__int__.py
cellrank_mcp/schema/estimator.py
cellrank_mcp/schema/kernel.py
cellrank_mcp/schema/pl.py
cellrank_mcp/schema/pp.py
cellrank_mcp/server/__init__.py
cellrank_mcp/server/preset/estimator.py
cellrank_mcp/server/preset/kernel.py
cellrank_mcp/server/preset/pl.py
cellrank_mcp/server/preset/pp.py
cellrank_mcp-0.4.0.dist-info/METADATA
cellrank_mcp-0.4.0.dist-info/WHEEL
cellrank_mcp-0.4.0.dist-info/entry_points.txt
cellrank_mcp-0.4.0.dist-info/RECORD
