Metadata-Version: 2.4
Name: cellrank-mcp
Version: 0.4.0
Summary: Natural language interface for dynamics from multi-view scRNA-Seq analysis with cellrank through MCP.
Project-URL: Homepage, http://scmcphub.org/
Project-URL: Repository, https://github.com/scmcphub/cellrank-mcp
Project-URL: Documentation, https://docs.scmcphub.org/
Author-email: shuang <hsh-me@outlook.com>
Keywords: AI,agent,bioinformatics,llm,mcp,model context protocol,scRNA-seq,single cell
Requires-Python: >=3.10
Requires-Dist: cellrank>=2.0.0
Requires-Dist: fastmcp>=2.3.4
Requires-Dist: mcp>=1.8.0
Requires-Dist: nest-asyncio
Requires-Dist: scmcp-shared>=0.5.0
